hiorco/__init__.py
hiorco/cli.py
hiorco/method.py
hiorco-1.0.0.dist-info/LICENSE
hiorco-1.0.0.dist-info/METADATA
hiorco-1.0.0.dist-info/WHEEL
hiorco-1.0.0.dist-info/entry_points.txt
hiorco-1.0.0.dist-info/top_level.txt
hiorco-1.0.0.dist-info/RECORD
