Metadata-Version: 2.1
Name: hiorco
Version: 1.0.0
Summary: Higher-Order Co-occurrence
Home-page: https://github.com/cdanielmachado/hiorco
Author: Daniel Machado
Author-email: cdanielmachado@gmail.com
License: Apache Software License 2.0
Keywords: hiorco
Platform: UNKNOWN
Classifier: Development Status :: 5 - Production/Stable
Classifier: License :: OSI Approved :: Apache Software License
Classifier: Natural Language :: English
Classifier: Programming Language :: Python :: 3.6
Requires-Python: >=3.6
